latynkatar/__init__.py
latynkatar/__init__.pyi
latynkatar/latynkatar.py
latynkatar/latynkatar.pyi
latynkatar/py.typed
latynkatar/variables.py
latynkatar/variables.pyi
latynkatar-2.0.2.dist-info/licenses/LICENSE
latynkatar-2.0.2.dist-info/METADATA
latynkatar-2.0.2.dist-info/WHEEL
latynkatar-2.0.2.dist-info/top_level.txt
latynkatar-2.0.2.dist-info/RECORD
