Metadata-Version: 2.4
Name: latynkatar
Version: 2.0.2
Summary: EN: Simple and small package to convert belarussian cyrillic text to a modern (the one with ž, č, š and v) and classic (the one with ż, cz, sz and w) latin .
Author-email: Andrej Zacharevicz <zahar.by@gmail.com>, Łatynkatar group <admin@latynkatar.org>
Project-URL: Homepage, https://github.com/latynkatar/latynkatar
Project-URL: Issues, https://github.com/latynkatar/latynkatar/issues
Classifier: Programming Language :: Python :: 3
Classifier: License :: OSI Approved :: GNU Lesser General Public License v3 (LGPLv3)
Classifier: Operating System :: OS Independent
Requires-Python: >=3.9
License-File: LICENSE
Dynamic: license-file
